sgp_agents/__init__.py
sgp_agents/_base_client.py
sgp_agents/_client.py
sgp_agents/_compat.py
sgp_agents/_constants.py
sgp_agents/_exceptions.py
sgp_agents/_files.py
sgp_agents/_models.py
sgp_agents/_qs.py
sgp_agents/_resource.py
sgp_agents/_response.py
sgp_agents/_streaming.py
sgp_agents/_types.py
sgp_agents/_version.py
sgp_agents/py.typed
sgp_agents/_utils/__init__.py
sgp_agents/_utils/_logs.py
sgp_agents/_utils/_proxy.py
sgp_agents/_utils/_reflection.py
sgp_agents/_utils/_streams.py
sgp_agents/_utils/_sync.py
sgp_agents/_utils/_transform.py
sgp_agents/_utils/_typing.py
sgp_agents/_utils/_utils.py
sgp_agents/lib/.keep
sgp_agents/resources/__init__.py
sgp_agents/resources/configs.py
sgp_agents/resources/health.py
sgp_agents/resources/healthz.py
sgp_agents/types/__init__.py
sgp_agents/types/config_create_and_execute_params.py
sgp_agents/types/config_create_and_execute_response.py
sgp_agents/types/config_create_params.py
sgp_agents/types/config_execute_params.py
sgp_agents/types/config_list_params.py
sgp_agents/types/execution_stream_response.py
sgp_agents/types/execution_sync_response.py
sgp_agents/types/plan_config_param.py
sgp_agents/types/workflow_config_param.py
scale_sgp_agents_python-0.0.1a1.dist-info/METADATA
scale_sgp_agents_python-0.0.1a1.dist-info/WHEEL
scale_sgp_agents_python-0.0.1a1.dist-info/licenses/LICENSE
scale_sgp_agents_python-0.0.1a1.dist-info/RECORD
